hockey_scraper/__init__.py
hockey_scraper/_version.py
hockey_scraper/setup.py
hockey_scraper/src/__init__.py
hockey_scraper/src/cli/__init__.py
hockey_scraper/src/cli/main.py
hockey_scraper/src/config/__init__.py
hockey_scraper/src/config/schemas.py
hockey_scraper/src/core/__init__.py
hockey_scraper/src/core/base_scraper.py
hockey_scraper/src/core/cleaners.py
hockey_scraper/src/core/factory.py
hockey_scraper/src/core/output_handler.py
hockey_scraper/src/core/utils.py
hockey_scraper/src/database/__init__.py
hockey_scraper/src/database/db.py
hockey_scraper/src/database/models.py
hockey_scraper/src/leagues/__init__.py
hockey_scraper/src/leagues/generic_scraper.py
hockey_scraper/src/leagues/nhl/__init__.py
hockey_scraper/src/leagues/nhl/analyzing.py
hockey_scraper/src/leagues/nhl/batch_pipelines.py
hockey_scraper/src/leagues/nhl/cleaning.py
hockey_scraper/src/leagues/nhl/constants.py
hockey_scraper/src/leagues/nhl/espn_integration.py
hockey_scraper/src/leagues/nhl/espn_pipeline.py
hockey_scraper/src/leagues/nhl/monitoring.py
hockey_scraper/src/leagues/nhl/parse.py
hockey_scraper/src/leagues/nhl/pipeline.py
hockey_scraper/src/leagues/nhl/reporting.py
hockey_scraper/src/leagues/nhl/scrape.py
hockey_scraper/src/leagues/nhl/storing.py
hockey_scraper/src/leagues/nhl/visualizing.py
hockey_scraper/src/leagues/ohl/__init__.py
hockey_scraper/src/leagues/ohl/parsers.py
hockey_scraper/src/leagues/ohl/scraper.py
hockey_scraper/src/leagues/qmjhl/__init__.py
hockey_scraper/src/leagues/qmjhl/parsers.py
hockey_scraper/src/leagues/qmjhl/scraper.py
hockey_scraper/src/leagues/whl/__init__.py
hockey_scraper/src/leagues/whl/parsers.py
hockey_scraper/src/leagues/whl/scraper.py
hockey_scraper/tests/__init__.py
hockey_scraper/tests/integration/test_nhl.py
hockey_scraper/tests/unit/test_output.py
hockey_scraper/tests/unit/test_parsers.py
hockey_scraper/tests/unit/test_utils.py
hockey_scraper_by_max-0.0.1.dev89.dist-info/licenses/LICENSE
hockey_scraper_by_max-0.0.1.dev89.dist-info/METADATA
hockey_scraper_by_max-0.0.1.dev89.dist-info/WHEEL
hockey_scraper_by_max-0.0.1.dev89.dist-info/top_level.txt
hockey_scraper_by_max-0.0.1.dev89.dist-info/RECORD
