Metadata-Version: 2.4
Name: hockey-scraper-by-max
Version: 0.0.1.dev89
Summary: A comprehensive Python package for scraping hockey data
Author-email: Max Tixador <maxtixador@gmail.com>
License-Expression: MIT
Project-URL: Homepage, https://github.com/maxtixador/hockey_scraper
Project-URL: Documentation, https://hockey-scraper.readthedocs.io
Project-URL: Repository, https://github.com/maxtixador/hockey_scraper.git
Project-URL: Issues, https://github.com/maxtixador/hockey_scraper/issues
Keywords: nhl,hockey,sports,data,api,espn,scraping,analytics
Classifier: Development Status :: 4 - Beta
Classifier: Intended Audience :: Developers
Classifier: Intended Audience :: Science/Research
Classifier: Programming Language :: Python :: 3 :: Only
Classifier: Programming Language :: Python :: 3.10
Classifier: Programming Language :: Python :: 3.11
Classifier: Programming Language :: Python :: 3.12
Classifier: Programming Language :: Python :: 3.13
Classifier: Topic :: Software Development :: Libraries :: Python Modules
Classifier: Topic :: Scientific/Engineering :: Information Analysis
Classifier: Topic :: Internet :: WWW/HTTP :: Dynamic Content
Requires-Python: >=3.10
License-File: LICENSE
Requires-Dist: pandas>=2.0.0
Requires-Dist: numpy>=1.20.0
Requires-Dist: polars>=1.20.0
Requires-Dist: requests>=2.25.0
Requires-Dist: aiohttp>=3.11.0
Requires-Dist: lxml>=4.9.0
Requires-Dist: beautifulsoup4>=4.9.0
Requires-Dist: selectolax>=0.3.0
Requires-Dist: playwright>=1.40.0
Requires-Dist: selenium>=4.15.0
Requires-Dist: webdriver-manager>=4.0.0
Requires-Dist: ftfy>=6.0.0
Requires-Dist: tqdm>=4.60.0
Requires-Dist: nest-asyncio>=1.5.0
Provides-Extra: dev
Requires-Dist: pytest>=7.0; extra == "dev"
Requires-Dist: pytest-cov>=4.0; extra == "dev"
Requires-Dist: pytest-asyncio>=0.25.0; extra == "dev"
Requires-Dist: mypy>=1.0; extra == "dev"
Requires-Dist: types-requests>=2.31; extra == "dev"
Requires-Dist: isort>=5.12; extra == "dev"
Requires-Dist: pandas-stubs; extra == "dev"
Requires-Dist: lxml-stubs; extra == "dev"
Requires-Dist: types-beautifulsoup4; extra == "dev"
Provides-Extra: viz
Requires-Dist: matplotlib>=3.5.0; extra == "viz"
Requires-Dist: seaborn>=0.11.0; extra == "viz"
Provides-Extra: notebook
Requires-Dist: jupyter>=1.0.0; extra == "notebook"
Requires-Dist: jupyterlab>=4.0.0; extra == "notebook"
Requires-Dist: ipykernel>=6.0.0; extra == "notebook"
Provides-Extra: dashboard
Requires-Dist: streamlit>=1.28.0; extra == "dashboard"
Provides-Extra: docs
Requires-Dist: mkdocs>=1.5.0; extra == "docs"
Requires-Dist: mkdocs-material>=9.0.0; extra == "docs"
Requires-Dist: mkdocstrings>=0.24.0; extra == "docs"
Requires-Dist: mkdocstrings-python>=1.7.0; extra == "docs"
Requires-Dist: mkdocs-gen-files>=0.5.0; extra == "docs"
Requires-Dist: mkdocs-literate-nav>=0.6.0; extra == "docs"
Requires-Dist: mkdocs-section-index>=0.3.0; extra == "docs"
Dynamic: license-file
